kessler/__init__.py
kessler/cdm.py
kessler/data.py
kessler/event.py
kessler/model.py
kessler/nn.py
kessler/observation_model.py
kessler/plot.py
kessler/util.py
kessler-1.0.1.dist-info/LICENSE.md
kessler-1.0.1.dist-info/METADATA
kessler-1.0.1.dist-info/WHEEL
kessler-1.0.1.dist-info/top_level.txt
kessler-1.0.1.dist-info/RECORD
