Metadata-Version: 2.2
Name: kessler
Version: 1.0.1
Summary: Machine learning and simulation-based inference and machine learning for space collision assessment and avoidance.
Home-page: https://kesslerlib.github.io/kessler/
Author: Giacomo Acciarini
Author-email: giacomo.acciarini@gmail.com
License: BSD
Keywords: Spacecraft Collision Avoidance Kessler Machine Learning Artificial Intelligence Probabilistic Programming
Classifier: License :: OSI Approved :: BSD License
Classifier: Programming Language :: Python :: 3
License-File: LICENSE.md
Requires-Dist: pyro-ppl
Requires-Dist: numpy
Requires-Dist: matplotlib
Requires-Dist: torch>=1.5.1
Requires-Dist: dsgp4
Requires-Dist: skyfield>=1.26
Requires-Dist: pandas
Provides-Extra: dev
Requires-Dist: pytest; extra == "dev"
Requires-Dist: coverage; extra == "dev"
Requires-Dist: pytest-xdist; extra == "dev"
Requires-Dist: scikit-learn; extra == "dev"
Dynamic: author
Dynamic: author-email
Dynamic: classifier
Dynamic: description
Dynamic: description-content-type
Dynamic: home-page
Dynamic: keywords
Dynamic: license
Dynamic: provides-extra
Dynamic: requires-dist
Dynamic: summary
